logsynth/__init__.py
logsynth/__main__.py
logsynth/cli.py
logsynth/config.py
logsynth/core/__init__.py
logsynth/core/corruptor.py
logsynth/core/generator.py
logsynth/core/output.py
logsynth/core/parallel.py
logsynth/core/rate_control.py
logsynth/examples/api-gateway.yaml
logsynth/fields/__init__.py
logsynth/fields/registry.py
logsynth/fields/types.py
logsynth/infer/__init__.py
logsynth/infer/detector.py
logsynth/infer/inference.py
logsynth/infer/parser.py
logsynth/llm/__init__.py
logsynth/llm/client.py
logsynth/llm/prompt2template.py
logsynth/llm/prompts.py
logsynth/presets/apache.yaml
logsynth/presets/audit.yaml
logsynth/presets/auth.yaml
logsynth/presets/docker.yaml
logsynth/presets/firewall.yaml
logsynth/presets/haproxy.yaml
logsynth/presets/java.yaml
logsynth/presets/kubernetes.yaml
logsynth/presets/mongodb.yaml
logsynth/presets/mysql.yaml
logsynth/presets/nginx-error.yaml
logsynth/presets/nginx.yaml
logsynth/presets/nodejs.yaml
logsynth/presets/postgres.yaml
logsynth/presets/python.yaml
logsynth/presets/redis.yaml
logsynth/presets/sshd.yaml
logsynth/presets/systemd.yaml
logsynth/presets/terraform.yaml
logsynth/replay/__init__.py
logsynth/replay/player.py
logsynth/tui/__init__.py
logsynth/tui/dashboard.py
logsynth/tui/stats.py
logsynth/utils/__init__.py
logsynth/utils/formatter.py
logsynth/utils/schema.py
logsynth/watch/__init__.py
logsynth/watch/tailer.py
logsynth-0.3.1.dist-info/METADATA
logsynth-0.3.1.dist-info/WHEEL
logsynth-0.3.1.dist-info/entry_points.txt
logsynth-0.3.1.dist-info/licenses/LICENSE
logsynth-0.3.1.dist-info/RECORD
