Metadata-Version: 2.4
Name: logsynth
Version: 0.3.1
Summary: Flexible synthetic log generator with YAML templates, rate control, and LLM-powered template synthesis
Author: Lance
License-Expression: MIT
License-File: LICENSE
Keywords: devops,generator,logging,synthetic,testing
Classifier: Development Status :: 4 - Beta
Classifier: Environment :: Console
Classifier: Intended Audience :: Developers
Classifier: Intended Audience :: System Administrators
Classifier: License :: OSI Approved :: MIT License
Classifier: Operating System :: OS Independent
Classifier: Programming Language :: Python :: 3
Classifier: Programming Language :: Python :: 3.11
Classifier: Programming Language :: Python :: 3.12
Classifier: Topic :: Software Development :: Testing
Classifier: Topic :: System :: Logging
Requires-Python: >=3.11
Requires-Dist: httpx>=0.25
Requires-Dist: jinja2>=3.1
Requires-Dist: pyyaml>=6.0
Requires-Dist: rich>=13.0
Requires-Dist: typer>=0.9.0
Provides-Extra: dev
Requires-Dist: pytest-cov; extra == 'dev'
Requires-Dist: pytest>=7.0; extra == 'dev'
Requires-Dist: ruff; extra == 'dev'
